LICENSE.txt
MANIFEST.in
README.md
setup.cfg
setup.py
minibuild/__init__.py
minibuild/__main__.py
minibuild/__version__.py
minibuild/actions_pool.py
minibuild/arch_parse.py
minibuild/build_art.py
minibuild/build_description.py
minibuild/build_workflow.py
minibuild/config_ini.py
minibuild/constants.py
minibuild/depends_check.py
minibuild/error_utils.py
minibuild/faccess_emerge.py
minibuild/gen_bconf.py
minibuild/grammar_subst.py
minibuild/makefile_core.py
minibuild/nasm_action.py
minibuild/os_utils.py
minibuild/osxapi_level.py
minibuild/parse_deffile.py
minibuild/pragma_tokens.py
minibuild/script_main.py
minibuild/spec_file.py
minibuild/ssp_stub.py
minibuild/string_utils.py
minibuild/toolset_base.py
minibuild/toolset_clang.py
minibuild/toolset_gcc.py
minibuild/toolset_msvs.py
minibuild/winapi_level.py
minibuild/winrc_manifest.py
minibuild.egg-info/PKG-INFO
minibuild.egg-info/SOURCES.txt
minibuild.egg-info/dependency_links.txt
minibuild.egg-info/top_level.txt
minibuild.egg-info/zip-safe