Metadata-Version: 2.1
Name: minibuild
Version: 1.0.9
Summary: Build system aimed to be a pure Python alternative to GNU Make with builtin support of MSVS, GCC, clang
Home-page: https://minibuild.github.io/minibuild/
Author: Vitaly Murashev
Author-email: vitaly.murashev@gmail.com
License: MIT
Download-URL: https://github.com/minibuild/minibuild/archive/1.0.9.tar.gz
Project-URL: Source, https://github.com/minibuild/minibuild/
Keywords: buildsystem build
Platform: Linux
Platform: Windows
Platform: MacOSX
Classifier: Development Status :: 5 - Production/Stable
Classifier: Environment :: Console
Classifier: License :: OSI Approved :: MIT License
Classifier: Operating System :: POSIX :: Linux
Classifier: Operating System :: MacOS :: MacOS X
Classifier: Operating System :: Microsoft :: Windows
Classifier: Programming Language :: Python
Classifier: Programming Language :: Python :: 2
Classifier: Programming Language :: Python :: 2.7
Classifier: Programming Language :: Python :: 3
Classifier: Programming Language :: Python :: Implementation :: CPython
Classifier: Topic :: Software Development :: Build Tools
Requires-Python: >=2.7
